nifpga/VERSION
nifpga/__init__.py
nifpga/bitfile.py
nifpga/nifpga.py
nifpga/session.py
nifpga/status.py
nifpga/statuscheckedlibrary.py
nifpga/tests/__init__.py
nifpga/tests/test_Cluster.py
nifpga/tests/test_FXP.py
nifpga/tests/test_bitfile.py
nifpga/tests/test_nifpga.py
nifpga-20.0.0.dist-info/LICENSE
nifpga-20.0.0.dist-info/METADATA
nifpga-20.0.0.dist-info/WHEEL
nifpga-20.0.0.dist-info/top_level.txt
nifpga-20.0.0.dist-info/RECORD
