Metadata-Version: 2.1
Name: nifpga
Version: 20.0.0
Summary: Python API for interacting with National Instrument's LabVIEW FPGA Devices
Home-page: https://github.com/ni/nifpga-python
Author: National Instruments
License: MIT
Platform: UNKNOWN
Classifier: Intended Audience :: End Users/Desktop
Classifier: Intended Audience :: Developers
Classifier: Operating System :: Microsoft :: Windows
Classifier: Operating System :: POSIX
Classifier: Programming Language :: Python
Classifier: License :: OSI Approved :: MIT License
Classifier: Topic :: Scientific/Engineering
Classifier: Topic :: Scientific/Engineering :: Human Machine Interfaces
Classifier: Topic :: Software Development :: Embedded Systems
Classifier: Topic :: System :: Hardware
Classifier: Topic :: System :: Hardware :: Hardware Drivers
Requires-Dist: future
Requires-Dist: enum34 ; python_version < "3.4"
